image_processor_lite-1.0.5.dist-info/licenses/LICENSE
imgprocessor/__init__.py
imgprocessor/math_utils.py
imgprocessor/optimization.py
imgprocessor/optimized_adapters.py
imgprocessor/config/__init__.py
imgprocessor/config/module_config.py
imgprocessor/cpp/CMakeLists.txt
imgprocessor/cpp/__init__.py
imgprocessor/cpp/bindings.py
imgprocessor/cpp/build_cpp.py
imgprocessor/cpp/geometry_utils.cpp
imgprocessor/cpp/image_filters.cpp
imgprocessor/cpp/build/CMakeCache.txt
imgprocessor/cpp/build/Makefile
imgprocessor/cpp/build/cmake_install.cmake
imgprocessor/cpp/build/libgeometry_utils.so
imgprocessor/cpp/build/libimage_filters.so
imgprocessor/distance_measurement/__init__.py
imgprocessor/distance_measurement/measurer.py
imgprocessor/shape_detection/__init__.py
imgprocessor/shape_detection/detector.py
imgprocessor/text_detection/__init__.py
imgprocessor/text_detection/detector.py
imgprocessor/text_detection/detector_optimized.py
imgprocessor/text_detection/fast_detector.py
imgprocessor/text_detection/ultra_fast_detector.py
imgprocessor/visual_analysis/__init__.py
imgprocessor/visual_analysis/_native.py
imgprocessor/visual_analysis/analyzer.py
imgprocessor/visual_analysis/setup_native.py
image_processor_lite-1.0.5.dist-info/METADATA
image_processor_lite-1.0.5.dist-info/WHEEL
image_processor_lite-1.0.5.dist-info/top_level.txt
image_processor_lite-1.0.5.dist-info/RECORD
