Metadata-Version: 2.4
Name: image-processor-lite
Version: 1.0.5
Summary: Package modulaire de traitement et d'analyse d'images avec modules C/C++ optimisés
Home-page: https://github.com/Maik-start/image-processor-lite
Author: ImageProcessor Team
Project-URL: Bug Reports, https://github.com/Maik-start/image-processor-lite/issues
Project-URL: Source, https://github.com/Maik-start/image-processor-lite
Project-URL: Documentation, https://github.com/Maik-start/image-processor-lite/wiki
Keywords: image processing opencv computer vision optimization
Classifier: Programming Language :: Python :: 3
Classifier: Programming Language :: Python :: 3.8
Classifier: Programming Language :: Python :: 3.9
Classifier: Programming Language :: Python :: 3.10
Classifier: Programming Language :: Python :: 3.11
Classifier: License :: OSI Approved :: MIT License
Classifier: Operating System :: OS Independent
Classifier: Intended Audience :: Developers
Classifier: Topic :: Multimedia :: Graphics :: Graphics Conversion
Classifier: Topic :: Scientific/Engineering :: Image Processing
Classifier: Development Status :: 5 - Production/Stable
Requires-Python: >=3.8
License-File: LICENSE
Requires-Dist: opencv-python>=4.5.0
Requires-Dist: numpy>=1.19.0
Provides-Extra: text-detection
Requires-Dist: easyocr>=1.6.0; extra == "text-detection"
Provides-Extra: text-detection-tesseract
Requires-Dist: pytesseract>=0.3.10; extra == "text-detection-tesseract"
Provides-Extra: optimization
Requires-Dist: cmake>=3.10; extra == "optimization"
Provides-Extra: dev
Requires-Dist: pytest>=7.0; extra == "dev"
Requires-Dist: pytest-cov>=3.0; extra == "dev"
Requires-Dist: black>=22.0; extra == "dev"
Requires-Dist: flake8>=4.0; extra == "dev"
Requires-Dist: mypy>=0.950; extra == "dev"
Dynamic: author
Dynamic: classifier
Dynamic: description
Dynamic: description-content-type
Dynamic: home-page
Dynamic: keywords
Dynamic: license-file
Dynamic: project-url
Dynamic: provides-extra
Dynamic: requires-dist
Dynamic: requires-python
Dynamic: summary
